{
  "Country": "游쉻릖 Italy",
  "City": "Imola",
  "Qual": "m치j. 18. 16:00",
  "Sprint": "-",
  "Race": "m치j. 19. 15:00",
  "QualDatePart": "m치jus 18.",
  "QualTimePart": "16:00",
  "SprintDatePart": "-",
  "SprintTimePart": "-",
  "RaceDatePart": "m치jus 19.",
  "RaceTimePart": "15:00",
  "Laps": "63",
  "Length": "4.9",
  "Distance": "309.1",
  "Bestlap": "1:15.484",
  "Bestlapdriver": "Hamilton, 2020",
  "FirstGP": "1980",
  "Trackimage": "https://elijahcreative.github.io/F1/Images/TR-Imola.png",
  "Track2": "https://elijahcreative.github.io/F1/Images2/TR-Imola.png"
}