{"Standings": [
    {
    "After":	"After Belgium"
    },
    {
    "Place":	"1",
    "Name":	"Verstappen",
    "Team":	"-",
    "Points":	"275"
    },
    {
    "Place":	"2",
    "Name":	"Norris",
    "Team":	"-",
    "Points":	"197"
    },
    {
    "Place":	"3",
    "Name":	"Leclerc",
    "Team":	"-",
    "Points":	"174"
    },
    {
    "Place":	"4",
    "Name":	"Piastri",
    "Team":	"-",
    "Points":	"164"
    },
    {
    "Place":	"5",
    "Name":	"Sainz",
    "Team":	"-",
    "Points":	"160"
    },
    {
    "Place":	"6",
    "Name":	"Hamilton",
    "Team":	"-",
    "Points":	"143"
    }
    ]}
