{
    "current_condition": [
        {
            "FeelsLikeC": "25",
            "FeelsLikeF": "76",
            "cloudcover": "0",
            "humidity": "18",
            "localObsDateTime": "2025-10-06 03:50 PM",
            "observation_time": "10:50 PM",
            "precipInches": "0.0",
            "precipMM": "0.0",
            "pressure": "1014",
            "pressureInches": "30",
            "temp_C": "26",
            "temp_F": "79",
            "uvIndex": "4",
            "visibility": "16",
            "visibilityMiles": "9",
            "weatherCode": "113",
            "weatherDesc": [
                {
                    "value": "Sunny"
                }
            ],
            "weatherIconUrl": [
                {
                    "value": ""
                }
            ],
            "winddir16Point": "E",
            "winddirDegree": "96",
            "windspeedKmph": "8",
            "windspeedMiles": "5"
        }
    ],
    "nearest_area": [
        {
            "areaName": [
                {
                    "value": "Coffee"
                }
            ],
            "country": [
                {
                    "value": "United States of America"
                }
            ],
            "latitude": "41.103",
            "longitude": "-122.777",
            "population": "0",
            "region": [
                {
                    "value": "California"
                }
            ],
            "weatherUrl": [
                {
                    "value": ""
                }
            ]
        }
    ],
    "request": [
        {
            "query": "Lat 41.19 and Lon -122.92",
            "type": "LatLon"
        }
    ],
    "weather": [
        {
            "astronomy": [
                {
                    "moon_illumination": "98",
                    "moon_phase": "Waxing Gibbous",
                    "moonrise": "06:26 PM",
                    "moonset": "06:38 AM",
                    "sunrise": "07:13 AM",
                    "sunset": "06:44 PM"
                }
            ],
            "avgtempC": "17",
            "avgtempF": "63",
            "date": "2025-10-06",
            "hourly": [
                {
                    "DewPointC": "-1",
                    "DewPointF": "30",
                    "FeelsLikeC": "11",
                    "FeelsLikeF": "52",
                    "HeatIndexC": "12",
                    "HeatIndexF": "54",
                    "WindChillC": "11",
                    "WindChillF": "52",
                    "WindGustKmph": "18",
                    "WindGustMiles": "11",
                    "chanceoffog": "0",
                    "chanceoffrost": "0",
                    "chanceofhightemp": "0",
                    "chanceofovercast": "0",
                    "chanceofrain": "0",
                    "chanceofremdry": "92",
                    "chanceofsnow": "0",
                    "chanceofsunshine": "92",
                    "chanceofthunder": "0",
                    "chanceofwindy": "0",
                    "cloudcover": "0",
                    "diffRad": "0.0",
                    "humidity": "40",
                    "precipInches": "0.0",
                    "precipMM": "0.0",
                    "pressure": "911",
                    "pressureInches": "27",
                    "shortRad": "0.0",
                    "tempC": "12",
                    "tempF": "54",
                    "time": "0",
                    "uvIndex": "0",
                    "visibility": "10",
                    "visibilityMiles": "6",
                    "weatherCode": "113",
                    "weatherDesc": [
                        {
                            "value": "Clear "
                        }
                    ],
                    "weatherIconUrl": [
                        {
                            "value": ""
                        }
                    ],
                    "winddir16Point": "NNW",
                    "winddirDegree": "348",
                    "windspeedKmph": "9",
                    "windspeedMiles": "5"
                },
                {
                    "DewPointC": "-1",
                    "DewPointF": "30",
                    "FeelsLikeC": "10",
                    "FeelsLikeF": "50",
                    "HeatIndexC": "11",
                    "HeatIndexF": "53",
                    "WindChillC": "10",
                    "WindChillF": "50",
                    "WindGustKmph": "18",
                    "WindGustMiles": "11",
                    "chanceoffog": "0",
                    "chanceoffrost": "0",
                    "chanceofhightemp": "0",
                    "chanceofovercast": "0",
                    "chanceofrain": "0",
                    "chanceofremdry": "82",
                    "chanceofsnow": "0",
                    "chanceofsunshine": "94",
                    "chanceofthunder": "0",
                    "chanceofwindy": "0",
                    "cloudcover": "0",
                    "diffRad": "0.0",
                    "humidity": "42",
                    "precipInches": "0.0",
                    "precipMM": "0.0",
                    "pressure": "910",
                    "pressureInches": "27",
                    "shortRad": "0.0",
                    "tempC": "11",
                    "tempF": "53",
                    "time": "300",
                    "uvIndex": "0",
                    "visibility": "10",
                    "visibilityMiles": "6",
                    "weatherCode": "113",
                    "weatherDesc": [
                        {
                            "value": "Clear "
                        }
                    ],
                    "weatherIconUrl": [
                        {
                            "value": ""
                        }
                    ],
                    "winddir16Point": "NNW",
                    "winddirDegree": "347",
                    "windspeedKmph": "9",
                    "windspeedMiles": "5"
                },
                {
                    "DewPointC": "-2",
                    "DewPointF": "29",
                    "FeelsLikeC": "10",
                    "FeelsLikeF": "49",
                    "HeatIndexC": "11",
                    "HeatIndexF": "52",
                    "WindChillC": "10",
                    "WindChillF": "49",
                    "WindGustKmph": "18",
                    "WindGustMiles": "11",
                    "chanceoffog": "0",
                    "chanceoffrost": "10",
                    "chanceofhightemp": "0",
                    "chanceofovercast": "0",
                    "chanceofrain": "0",
                    "chanceofremdry": "82",
                    "chanceofsnow": "0",
                    "chanceofsunshine": "94",
                    "chanceofthunder": "0",
                    "chanceofwindy": "0",
                    "cloudcover": "0",
                    "diffRad": "0.0",
                    "humidity": "41",
                    "precipInches": "0.0",
                    "precipMM": "0.0",
                    "pressure": "911",
                    "pressureInches": "27",
                    "shortRad": "0.0",
                    "tempC": "11",
                    "tempF": "52",
                    "time": "600",
                    "uvIndex": "0",
                    "visibility": "10",
                    "visibilityMiles": "6",
                    "weatherCode": "113",
                    "weatherDesc": [
                        {
                            "value": "Clear "
                        }
                    ],
                    "weatherIconUrl": [
                        {
                            "value": ""
                        }
                    ],
                    "winddir16Point": "N",
                    "winddirDegree": "349",
                    "windspeedKmph": "9",
                    "windspeedMiles": "5"
                },
                {
                    "DewPointC": "-0",
                    "DewPointF": "32",
                    "FeelsLikeC": "14",
                    "FeelsLikeF": "58",
                    "HeatIndexC": "15",
                    "HeatIndexF": "58",
                    "WindChillC": "14",
                    "WindChillF": "58",
                    "WindGustKmph": "8",
                    "WindGustMiles": "5",
                    "chanceoffog": "0",
                    "chanceoffrost": "0",
                    "chanceofhightemp": "0",
                    "chanceofovercast": "0",
                    "chanceofrain": "0",
                    "chanceofremdry": "87",
                    "chanceofsnow": "0",
                    "chanceofsunshine": "92",
                    "chanceofthunder": "0",
                    "chanceofwindy": "0",
                    "cloudcover": "0",
                    "diffRad": "13.0",
                    "humidity": "39",
                    "precipInches": "0.0",
                    "precipMM": "0.0",
                    "pressure": "911",
                    "pressureInches": "27",
                    "shortRad": "57.9",
                    "tempC": "15",
                    "tempF": "58",
                    "time": "900",
                    "uvIndex": "1",
                    "visibility": "10",
                    "visibilityMiles": "6",
                    "weatherCode": "113",
                    "weatherDesc": [
                        {
                            "value": "Sunny"
                        }
                    ],
                    "weatherIconUrl": [
                        {
                            "value": ""
                        }
                    ],
                    "winddir16Point": "NNE",
                    "winddirDegree": "17",
                    "windspeedKmph": "7",
                    "windspeedMiles": "4"
                },
                {
                    "DewPointC": "3",
                    "DewPointF": "37",
                    "FeelsLikeC": "22",
                    "FeelsLikeF": "71",
                    "HeatIndexC": "22",
                    "HeatIndexF": "71",
                    "WindChillC": "22",
                    "WindChillF": "71",
                    "WindGustKmph": "9",
                    "WindGustMiles": "5",
                    "chanceoffog": "0",
                    "chanceoffrost": "0",
                    "chanceofhightemp": "0",
                    "chanceofovercast": "0",
                    "chanceofrain": "0",
                    "chanceofremdry": "87",
                    "chanceofsnow": "0",
                    "chanceofsunshine": "85",
                    "chanceofthunder": "0",
                    "chanceofwindy": "0",
                    "cloudcover": "0",
                    "diffRad": "64.4",
                    "humidity": "27",
                    "precipInches": "0.0",
                    "precipMM": "0.0",
                    "pressure": "911",
                    "pressureInches": "27",
                    "shortRad": "680.9",
                    "tempC": "22",
                    "tempF": "71",
                    "time": "1200",
                    "uvIndex": "5",
                    "visibility": "10",
                    "visibilityMiles": "6",
                    "weatherCode": "113",
                    "weatherDesc": [
                        {
                            "value": "Sunny"
                        }
                    ],
                    "weatherIconUrl": [
                        {
                            "value": ""
                        }
                    ],
                    "winddir16Point": "E",
                    "winddirDegree": "87",
                    "windspeedKmph": "8",
                    "windspeedMiles": "5"
                },
                {
                    "DewPointC": "1",
                    "DewPointF": "34",
                    "FeelsLikeC": "24",
                    "FeelsLikeF": "75",
                    "HeatIndexC": "24",
                    "HeatIndexF": "75",
                    "WindChillC": "25",
                    "WindChillF": "77",
                    "WindGustKmph": "9",
                    "WindGustMiles": "5",
                    "chanceoffog": "0",
                    "chanceoffrost": "0",
                    "chanceofhightemp": "10",
                    "chanceofovercast": "0",
                    "chanceofrain": "0",
                    "chanceofremdry": "86",
                    "chanceofsnow": "0",
                    "chanceofsunshine": "86",
                    "chanceofthunder": "0",
                    "chanceofwindy": "0",
                    "cloudcover": "0",
                    "diffRad": "64.9",
                    "humidity": "18",
                    "precipInches": "0.0",
                    "precipMM": "0.0",
                    "pressure": "1014",
                    "pressureInches": "30",
                    "shortRad": "710.1",
                    "tempC": "26",
                    "tempF": "79",
                    "time": "1500",
                    "uvIndex": "4",
                    "visibility": "16",
                    "visibilityMiles": "9",
                    "weatherCode": "113",
                    "weatherDesc": [
                        {
                            "value": "Sunny"
                        }
                    ],
                    "weatherIconUrl": [
                        {
                            "value": ""
                        }
                    ],
                    "winddir16Point": "E",
                    "winddirDegree": "96",
                    "windspeedKmph": "8",
                    "windspeedMiles": "5"
                },
                {
                    "DewPointC": "-0",
                    "DewPointF": "32",
                    "FeelsLikeC": "23",
                    "FeelsLikeF": "73",
                    "HeatIndexC": "23",
                    "HeatIndexF": "73",
                    "WindChillC": "23",
                    "WindChillF": "74",
                    "WindGustKmph": "5",
                    "WindGustMiles": "3",
                    "chanceoffog": "0",
                    "chanceoffrost": "0",
                    "chanceofhightemp": "0",
                    "chanceofovercast": "0",
                    "chanceofrain": "0",
                    "chanceofremdry": "93",
                    "chanceofsnow": "0",
                    "chanceofsunshine": "86",
                    "chanceofthunder": "0",
                    "chanceofwindy": "0",
                    "cloudcover": "0",
                    "diffRad": "39.1",
                    "humidity": "20",
                    "precipInches": "0.0",
                    "precipMM": "0.0",
                    "pressure": "909",
                    "pressureInches": "27",
                    "shortRad": "192.4",
                    "tempC": "23",
                    "tempF": "74",
                    "time": "1800",
                    "uvIndex": "0",
                    "visibility": "10",
                    "visibilityMiles": "6",
                    "weatherCode": "113",
                    "weatherDesc": [
                        {
                            "value": "Sunny"
                        }
                    ],
                    "weatherIconUrl": [
                        {
                            "value": ""
                        }
                    ],
                    "winddir16Point": "ENE",
                    "winddirDegree": "65",
                    "windspeedKmph": "3",
                    "windspeedMiles": "2"
                },
                {
                    "DewPointC": "-4",
                    "DewPointF": "25",
                    "FeelsLikeC": "18",
                    "FeelsLikeF": "64",
                    "HeatIndexC": "18",
                    "HeatIndexF": "64",
                    "WindChillC": "18",
                    "WindChillF": "64",
                    "WindGustKmph": "12",
                    "WindGustMiles": "8",
                    "chanceoffog": "0",
                    "chanceoffrost": "0",
                    "chanceofhightemp": "0",
                    "chanceofovercast": "0",
                    "chanceofrain": "0",
                    "chanceofremdry": "82",
                    "chanceofsnow": "0",
                    "chanceofsunshine": "94",
                    "chanceofthunder": "0",
                    "chanceofwindy": "0",
                    "cloudcover": "0",
                    "diffRad": "12.1",
                    "humidity": "22",
                    "precipInches": "0.0",
                    "precipMM": "0.0",
                    "pressure": "911",
                    "pressureInches": "27",
                    "shortRad": "54.3",
                    "tempC": "18",
                    "tempF": "64",
                    "time": "2100",
                    "uvIndex": "0",
                    "visibility": "10",
                    "visibilityMiles": "6",
                    "weatherCode": "113",
                    "weatherDesc": [
                        {
                            "value": "Clear "
                        }
                    ],
                    "weatherIconUrl": [
                        {
                            "value": ""
                        }
                    ],
                    "winddir16Point": "NNW",
                    "winddirDegree": "344",
                    "windspeedKmph": "6",
                    "windspeedMiles": "4"
                }
            ],
            "maxtempC": "26",
            "maxtempF": "78",
            "mintempC": "11",
            "mintempF": "51",
            "sunHour": "11.0",
            "totalSnow_cm": "0.0",
            "uvIndex": "1"
        },
        {
            "astronomy": [
                {
                    "moon_illumination": "100",
                    "moon_phase": "Full Moon",
                    "moonrise": "06:53 PM",
                    "moonset": "07:56 AM",
                    "sunrise": "07:14 AM",
                    "sunset": "06:42 PM"
                }
            ],
            "avgtempC": "15",
            "avgtempF": "59",
            "date": "2025-10-07",
            "hourly": [
                {
                    "DewPointC": "-6",
                    "DewPointF": "22",
                    "FeelsLikeC": "10",
                    "FeelsLikeF": "51",
                    "HeatIndexC": "11",
                    "HeatIndexF": "52",
                    "WindChillC": "10",
                    "WindChillF": "51",
                    "WindGustKmph": "14",
                    "WindGustMiles": "8",
                    "chanceoffog": "0",
                    "chanceoffrost": "0",
                    "chanceofhightemp": "0",
                    "chanceofovercast": "0",
                    "chanceofrain": "0",
                    "chanceofremdry": "83",
                    "chanceofsnow": "0",
                    "chanceofsunshine": "93",
                    "chanceofthunder": "0",
                    "chanceofwindy": "0",
                    "cloudcover": "0",
                    "diffRad": "0.0",
                    "humidity": "34",
                    "precipInches": "0.0",
                    "precipMM": "0.0",
                    "pressure": "913",
                    "pressureInches": "27",
                    "shortRad": "0.0",
                    "tempC": "11",
                    "tempF": "52",
                    "time": "0",
                    "uvIndex": "0",
                    "visibility": "10",
                    "visibilityMiles": "6",
                    "weatherCode": "113",
                    "weatherDesc": [
                        {
                            "value": "Clear "
                        }
                    ],
                    "weatherIconUrl": [
                        {
                            "value": ""
                        }
                    ],
                    "winddir16Point": "NNW",
                    "winddirDegree": "341",
                    "windspeedKmph": "6",
                    "windspeedMiles": "4"
                },
                {
                    "DewPointC": "-5",
                    "DewPointF": "22",
                    "FeelsLikeC": "7",
                    "FeelsLikeF": "45",
                    "HeatIndexC": "8",
                    "HeatIndexF": "46",
                    "WindChillC": "7",
                    "WindChillF": "45",
                    "WindGustKmph": "14",
                    "WindGustMiles": "8",
                    "chanceoffog": "0",
                    "chanceoffrost": "0",
                    "chanceofhightemp": "0",
                    "chanceofovercast": "0",
                    "chanceofrain": "0",
                    "chanceofremdry": "84",
                    "chanceofsnow": "0",
                    "chanceofsunshine": "89",
                    "chanceofthunder": "0",
                    "chanceofwindy": "0",
                    "cloudcover": "0",
                    "diffRad": "0.0",
                    "humidity": "40",
                    "precipInches": "0.0",
                    "precipMM": "0.0",
                    "pressure": "919",
                    "pressureInches": "27",
                    "shortRad": "0.0",
                    "tempC": "8",
                    "tempF": "46",
                    "time": "300",
                    "uvIndex": "0",
                    "visibility": "10",
                    "visibilityMiles": "6",
                    "weatherCode": "113",
                    "weatherDesc": [
                        {
                            "value": "Clear "
                        }
                    ],
                    "weatherIconUrl": [
                        {
                            "value": ""
                        }
                    ],
                    "winddir16Point": "NNW",
                    "winddirDegree": "336",
                    "windspeedKmph": "6",
                    "windspeedMiles": "4"
                },
                {
                    "DewPointC": "-4",
                    "DewPointF": "24",
                    "FeelsLikeC": "6",
                    "FeelsLikeF": "42",
                    "HeatIndexC": "7",
                    "HeatIndexF": "44",
                    "WindChillC": "6",
                    "WindChillF": "42",
                    "WindGustKmph": "14",
                    "WindGustMiles": "9",
                    "chanceoffog": "0",
                    "chanceoffrost": "0",
                    "chanceofhightemp": "0",
                    "chanceofovercast": "0",
                    "chanceofrain": "0",
                    "chanceofremdry": "88",
                    "chanceofsnow": "0",
                    "chanceofsunshine": "91",
                    "chanceofthunder": "0",
                    "chanceofwindy": "0",
                    "cloudcover": "0",
                    "diffRad": "0.0",
                    "humidity": "46",
                    "precipInches": "0.0",
                    "precipMM": "0.0",
                    "pressure": "925",
                    "pressureInches": "27",
                    "shortRad": "0.0",
                    "tempC": "7",
                    "tempF": "44",
                    "time": "600",
                    "uvIndex": "0",
                    "visibility": "10",
                    "visibilityMiles": "6",
                    "weatherCode": "113",
                    "weatherDesc": [
                        {
                            "value": "Clear "
                        }
                    ],
                    "weatherIconUrl": [
                        {
                            "value": ""
                        }
                    ],
                    "winddir16Point": "NNW",
                    "winddirDegree": "337",
                    "windspeedKmph": "7",
                    "windspeedMiles": "4"
                },
                {
                    "DewPointC": "-2",
                    "DewPointF": "28",
                    "FeelsLikeC": "12",
                    "FeelsLikeF": "54",
                    "HeatIndexC": "13",
                    "HeatIndexF": "55",
                    "WindChillC": "12",
                    "WindChillF": "54",
                    "WindGustKmph": "4",
                    "WindGustMiles": "2",
                    "chanceoffog": "0",
                    "chanceoffrost": "0",
                    "chanceofhightemp": "0",
                    "chanceofovercast": "0",
                    "chanceofrain": "0",
                    "chanceofremdry": "87",
                    "chanceofsnow": "0",
                    "chanceofsunshine": "87",
                    "chanceofthunder": "0",
                    "chanceofwindy": "0",
                    "cloudcover": "0",
                    "diffRad": "12.6",
                    "humidity": "48",
                    "precipInches": "0.0",
                    "precipMM": "0.0",
                    "pressure": "931",
                    "pressureInches": "27",
                    "shortRad": "56.5",
                    "tempC": "13",
                    "tempF": "55",
                    "time": "900",
                    "uvIndex": "1",
                    "visibility": "10",
                    "visibilityMiles": "6",
                    "weatherCode": "113",
                    "weatherDesc": [
                        {
                            "value": "Sunny"
                        }
                    ],
                    "weatherIconUrl": [
                        {
                            "value": ""
                        }
                    ],
                    "winddir16Point": "N",
                    "winddirDegree": "1",
                    "windspeedKmph": "3",
                    "windspeedMiles": "2"
                },
                {
                    "DewPointC": "3",
                    "DewPointF": "38",
                    "FeelsLikeC": "23",
                    "FeelsLikeF": "73",
                    "HeatIndexC": "23",
                    "HeatIndexF": "73",
                    "WindChillC": "23",
                    "WindChillF": "73",
                    "WindGustKmph": "4",
                    "WindGustMiles": "3",
                    "chanceoffog": "0",
                    "chanceoffrost": "0",
                    "chanceofhightemp": "15",
                    "chanceofovercast": "0",
                    "chanceofrain": "0",
                    "chanceofremdry": "84",
                    "chanceofsnow": "0",
                    "chanceofsunshine": "89",
                    "chanceofthunder": "0",
                    "chanceofwindy": "0",
                    "cloudcover": "0",
                    "diffRad": "64.8",
                    "humidity": "26",
                    "precipInches": "0.0",
                    "precipMM": "0.0",
                    "pressure": "937",
                    "pressureInches": "28",
                    "shortRad": "672.7",
                    "tempC": "23",
                    "tempF": "73",
                    "time": "1200",
                    "uvIndex": "4",
                    "visibility": "10",
                    "visibilityMiles": "6",
                    "weatherCode": "113",
                    "weatherDesc": [
                        {
                            "value": "Sunny"
                        }
                    ],
                    "weatherIconUrl": [
                        {
                            "value": ""
                        }
                    ],
                    "winddir16Point": "SSE",
                    "winddirDegree": "148",
                    "windspeedKmph": "4",
                    "windspeedMiles": "2"
                },
                {
                    "DewPointC": "4",
                    "DewPointF": "39",
                    "FeelsLikeC": "24",
                    "FeelsLikeF": "76",
                    "HeatIndexC": "24",
                    "HeatIndexF": "76",
                    "WindChillC": "25",
                    "WindChillF": "78",
                    "WindGustKmph": "6",
                    "WindGustMiles": "4",
                    "chanceoffog": "0",
                    "chanceoffrost": "0",
                    "chanceofhightemp": "86",
                    "chanceofovercast": "0",
                    "chanceofrain": "0",
                    "chanceofremdry": "81",
                    "chanceofsnow": "0",
                    "chanceofsunshine": "89",
                    "chanceofthunder": "0",
                    "chanceofwindy": "0",
                    "cloudcover": "0",
                    "diffRad": "65.7",
                    "humidity": "25",
                    "precipInches": "0.0",
                    "precipMM": "0.0",
                    "pressure": "943",
                    "pressureInches": "28",
                    "shortRad": "698.9",
                    "tempC": "25",
                    "tempF": "78",
                    "time": "1500",
                    "uvIndex": "4",
                    "visibility": "10",
                    "visibilityMiles": "6",
                    "weatherCode": "113",
                    "weatherDesc": [
                        {
                            "value": "Sunny"
                        }
                    ],
                    "weatherIconUrl": [
                        {
                            "value": ""
                        }
                    ],
                    "winddir16Point": "SSE",
                    "winddirDegree": "157",
                    "windspeedKmph": "5",
                    "windspeedMiles": "3"
                },
                {
                    "DewPointC": "3",
                    "DewPointF": "37",
                    "FeelsLikeC": "21",
                    "FeelsLikeF": "71",
                    "HeatIndexC": "21",
                    "HeatIndexF": "70",
                    "WindChillC": "21",
                    "WindChillF": "71",
                    "WindGustKmph": "5",
                    "WindGustMiles": "3",
                    "chanceoffog": "0",
                    "chanceoffrost": "0",
                    "chanceofhightemp": "0",
                    "chanceofovercast": "0",
                    "chanceofrain": "0",
                    "chanceofremdry": "87",
                    "chanceofsnow": "0",
                    "chanceofsunshine": "88",
                    "chanceofthunder": "0",
                    "chanceofwindy": "0",
                    "cloudcover": "0",
                    "diffRad": "38.9",
                    "humidity": "30",
                    "precipInches": "0.0",
                    "precipMM": "0.0",
                    "pressure": "949",
                    "pressureInches": "28",
                    "shortRad": "183.2",
                    "tempC": "21",
                    "tempF": "71",
                    "time": "1800",
                    "uvIndex": "0",
                    "visibility": "10",
                    "visibilityMiles": "6",
                    "weatherCode": "113",
                    "weatherDesc": [
                        {
                            "value": "Sunny"
                        }
                    ],
                    "weatherIconUrl": [
                        {
                            "value": ""
                        }
                    ],
                    "winddir16Point": "SE",
                    "winddirDegree": "135",
                    "windspeedKmph": "2",
                    "windspeedMiles": "1"
                },
                {
                    "DewPointC": "-1",
                    "DewPointF": "31",
                    "FeelsLikeC": "15",
                    "FeelsLikeF": "59",
                    "HeatIndexC": "14",
                    "HeatIndexF": "58",
                    "WindChillC": "15",
                    "WindChillF": "59",
                    "WindGustKmph": "11",
                    "WindGustMiles": "7",
                    "chanceoffog": "0",
                    "chanceoffrost": "0",
                    "chanceofhightemp": "0",
                    "chanceofovercast": "0",
                    "chanceofrain": "0",
                    "chanceofremdry": "82",
                    "chanceofsnow": "0",
                    "chanceofsunshine": "91",
                    "chanceofthunder": "0",
                    "chanceofwindy": "0",
                    "cloudcover": "0",
                    "diffRad": "11.8",
                    "humidity": "36",
                    "precipInches": "0.0",
                    "precipMM": "0.0",
                    "pressure": "955",
                    "pressureInches": "28",
                    "shortRad": "51.3",
                    "tempC": "15",
                    "tempF": "58",
                    "time": "2100",
                    "uvIndex": "0",
                    "visibility": "10",
                    "visibilityMiles": "6",
                    "weatherCode": "113",
                    "weatherDesc": [
                        {
                            "value": "Clear "
                        }
                    ],
                    "weatherIconUrl": [
                        {
                            "value": ""
                        }
                    ],
                    "winddir16Point": "NW",
                    "winddirDegree": "307",
                    "windspeedKmph": "5",
                    "windspeedMiles": "3"
                }
            ],
            "maxtempC": "26",
            "maxtempF": "78",
            "mintempC": "6",
            "mintempF": "43",
            "sunHour": "11.0",
            "totalSnow_cm": "0.0",
            "uvIndex": "1"
        },
        {
            "astronomy": [
                {
                    "moon_illumination": "99",
                    "moon_phase": "Waning Gibbous",
                    "moonrise": "07:24 PM",
                    "moonset": "09:17 AM",
                    "sunrise": "07:16 AM",
                    "sunset": "06:40 PM"
                }
            ],
            "avgtempC": "15",
            "avgtempF": "59",
            "date": "2025-10-08",
            "hourly": [
                {
                    "DewPointC": "-3",
                    "DewPointF": "27",
                    "FeelsLikeC": "10",
                    "FeelsLikeF": "50",
                    "HeatIndexC": "10",
                    "HeatIndexF": "50",
                    "WindChillC": "10",
                    "WindChillF": "50",
                    "WindGustKmph": "11",
                    "WindGustMiles": "7",
                    "chanceoffog": "0",
                    "chanceoffrost": "0",
                    "chanceofhightemp": "0",
                    "chanceofovercast": "0",
                    "chanceofrain": "0",
                    "chanceofremdry": "83",
                    "chanceofsnow": "0",
                    "chanceofsunshine": "91",
                    "chanceofthunder": "0",
                    "chanceofwindy": "0",
                    "cloudcover": "0",
                    "diffRad": "0.0",
                    "humidity": "41",
                    "precipInches": "0.0",
                    "precipMM": "0.0",
                    "pressure": "961",
                    "pressureInches": "28",
                    "shortRad": "0.0",
                    "tempC": "10",
                    "tempF": "50",
                    "time": "0",
                    "uvIndex": "0",
                    "visibility": "10",
                    "visibilityMiles": "6",
                    "weatherCode": "113",
                    "weatherDesc": [
                        {
                            "value": "Clear "
                        }
                    ],
                    "weatherIconUrl": [
                        {
                            "value": ""
                        }
                    ],
                    "winddir16Point": "WNW",
                    "winddirDegree": "297",
                    "windspeedKmph": "5",
                    "windspeedMiles": "3"
                },
                {
                    "DewPointC": "-3",
                    "DewPointF": "27",
                    "FeelsLikeC": "9",
                    "FeelsLikeF": "48",
                    "HeatIndexC": "9",
                    "HeatIndexF": "48",
                    "WindChillC": "9",
                    "WindChillF": "48",
                    "WindGustKmph": "8",
                    "WindGustMiles": "5",
                    "chanceoffog": "0",
                    "chanceoffrost": "0",
                    "chanceofhightemp": "0",
                    "chanceofovercast": "0",
                    "chanceofrain": "0",
                    "chanceofremdry": "93",
                    "chanceofsnow": "0",
                    "chanceofsunshine": "92",
                    "chanceofthunder": "0",
                    "chanceofwindy": "0",
                    "cloudcover": "0",
                    "diffRad": "0.0",
                    "humidity": "45",
                    "precipInches": "0.0",
                    "precipMM": "0.0",
                    "pressure": "967",
                    "pressureInches": "29",
                    "shortRad": "0.0",
                    "tempC": "9",
                    "tempF": "48",
                    "time": "300",
                    "uvIndex": "0",
                    "visibility": "10",
                    "visibilityMiles": "6",
                    "weatherCode": "113",
                    "weatherDesc": [
                        {
                            "value": "Clear "
                        }
                    ],
                    "weatherIconUrl": [
                        {
                            "value": ""
                        }
                    ],
                    "winddir16Point": "WNW",
                    "winddirDegree": "292",
                    "windspeedKmph": "4",
                    "windspeedMiles": "2"
                },
                {
                    "DewPointC": "-3",
                    "DewPointF": "27",
                    "FeelsLikeC": "8",
                    "FeelsLikeF": "46",
                    "HeatIndexC": "8",
                    "HeatIndexF": "46",
                    "WindChillC": "8",
                    "WindChillF": "46",
                    "WindGustKmph": "6",
                    "WindGustMiles": "4",
                    "chanceoffog": "0",
                    "chanceoffrost": "0",
                    "chanceofhightemp": "0",
                    "chanceofovercast": "0",
                    "chanceofrain": "0",
                    "chanceofremdry": "87",
                    "chanceofsnow": "0",
                    "chanceofsunshine": "88",
                    "chanceofthunder": "0",
                    "chanceofwindy": "0",
                    "cloudcover": "0",
                    "diffRad": "0.0",
                    "humidity": "47",
                    "precipInches": "0.0",
                    "precipMM": "0.0",
                    "pressure": "973",
                    "pressureInches": "29",
                    "shortRad": "0.0",
                    "tempC": "8",
                    "tempF": "46",
                    "time": "600",
                    "uvIndex": "0",
                    "visibility": "10",
                    "visibilityMiles": "6",
                    "weatherCode": "113",
                    "weatherDesc": [
                        {
                            "value": "Clear "
                        }
                    ],
                    "weatherIconUrl": [
                        {
                            "value": ""
                        }
                    ],
                    "winddir16Point": "WNW",
                    "winddirDegree": "290",
                    "windspeedKmph": "3",
                    "windspeedMiles": "2"
                },
                {
                    "DewPointC": "-1",
                    "DewPointF": "31",
                    "FeelsLikeC": "14",
                    "FeelsLikeF": "57",
                    "HeatIndexC": "14",
                    "HeatIndexF": "57",
                    "WindChillC": "14",
                    "WindChillF": "57",
                    "WindGustKmph": "5",
                    "WindGustMiles": "3",
                    "chanceoffog": "0",
                    "chanceoffrost": "0",
                    "chanceofhightemp": "0",
                    "chanceofovercast": "0",
                    "chanceofrain": "0",
                    "chanceofremdry": "88",
                    "chanceofsnow": "0",
                    "chanceofsunshine": "86",
                    "chanceofthunder": "0",
                    "chanceofwindy": "0",
                    "cloudcover": "0",
                    "diffRad": "12.8",
                    "humidity": "38",
                    "precipInches": "0.0",
                    "precipMM": "0.0",
                    "pressure": "979",
                    "pressureInches": "29",
                    "shortRad": "53.8",
                    "tempC": "14",
                    "tempF": "57",
                    "time": "900",
                    "uvIndex": "1",
                    "visibility": "10",
                    "visibilityMiles": "6",
                    "weatherCode": "113",
                    "weatherDesc": [
                        {
                            "value": "Sunny"
                        }
                    ],
                    "weatherIconUrl": [
                        {
                            "value": ""
                        }
                    ],
                    "winddir16Point": "S",
                    "winddirDegree": "176",
                    "windspeedKmph": "4",
                    "windspeedMiles": "2"
                },
                {
                    "DewPointC": "2",
                    "DewPointF": "36",
                    "FeelsLikeC": "21",
                    "FeelsLikeF": "70",
                    "HeatIndexC": "21",
                    "HeatIndexF": "70",
                    "WindChillC": "21",
                    "WindChillF": "70",
                    "WindGustKmph": "16",
                    "WindGustMiles": "10",
                    "chanceoffog": "0",
                    "chanceoffrost": "0",
                    "chanceofhightemp": "0",
                    "chanceofovercast": "0",
                    "chanceofrain": "0",
                    "chanceofremdry": "90",
                    "chanceofsnow": "0",
                    "chanceofsunshine": "94",
                    "chanceofthunder": "0",
                    "chanceofwindy": "0",
                    "cloudcover": "0",
                    "diffRad": "69.1",
                    "humidity": "28",
                    "precipInches": "0.0",
                    "precipMM": "0.0",
                    "pressure": "985",
                    "pressureInches": "29",
                    "shortRad": "655.4",
                    "tempC": "21",
                    "tempF": "70",
                    "time": "1200",
                    "uvIndex": "4",
                    "visibility": "10",
                    "visibilityMiles": "6",
                    "weatherCode": "113",
                    "weatherDesc": [
                        {
                            "value": "Sunny"
                        }
                    ],
                    "weatherIconUrl": [
                        {
                            "value": ""
                        }
                    ],
                    "winddir16Point": "SSW",
                    "winddirDegree": "193",
                    "windspeedKmph": "14",
                    "windspeedMiles": "9"
                },
                {
                    "DewPointC": "3",
                    "DewPointF": "37",
                    "FeelsLikeC": "23",
                    "FeelsLikeF": "73",
                    "HeatIndexC": "23",
                    "HeatIndexF": "73",
                    "WindChillC": "22",
                    "WindChillF": "72",
                    "WindGustKmph": "23",
                    "WindGustMiles": "14",
                    "chanceoffog": "0",
                    "chanceoffrost": "0",
                    "chanceofhightemp": "10",
                    "chanceofovercast": "0",
                    "chanceofrain": "0",
                    "chanceofremdry": "94",
                    "chanceofsnow": "0",
                    "chanceofsunshine": "90",
                    "chanceofthunder": "0",
                    "chanceofwindy": "0",
                    "cloudcover": "0",
                    "diffRad": "70.5",
                    "humidity": "28",
                    "precipInches": "0.0",
                    "precipMM": "0.0",
                    "pressure": "991",
                    "pressureInches": "29",
                    "shortRad": "681.3",
                    "tempC": "22",
                    "tempF": "72",
                    "time": "1500",
                    "uvIndex": "3",
                    "visibility": "10",
                    "visibilityMiles": "6",
                    "weatherCode": "113",
                    "weatherDesc": [
                        {
                            "value": "Sunny"
                        }
                    ],
                    "weatherIconUrl": [
                        {
                            "value": ""
                        }
                    ],
                    "winddir16Point": "SW",
                    "winddirDegree": "223",
                    "windspeedKmph": "20",
                    "windspeedMiles": "13"
                },
                {
                    "DewPointC": "3",
                    "DewPointF": "38",
                    "FeelsLikeC": "19",
                    "FeelsLikeF": "67",
                    "HeatIndexC": "20",
                    "HeatIndexF": "68",
                    "WindChillC": "19",
                    "WindChillF": "67",
                    "WindGustKmph": "12",
                    "WindGustMiles": "8",
                    "chanceoffog": "0",
                    "chanceoffrost": "0",
                    "chanceofhightemp": "0",
                    "chanceofovercast": "0",
                    "chanceofrain": "0",
                    "chanceofremdry": "93",
                    "chanceofsnow": "0",
                    "chanceofsunshine": "89",
                    "chanceofthunder": "0",
                    "chanceofwindy": "0",
                    "cloudcover": "0",
                    "diffRad": "52.8",
                    "humidity": "35",
                    "precipInches": "0.0",
                    "precipMM": "0.0",
                    "pressure": "997",
                    "pressureInches": "29",
                    "shortRad": "150.2",
                    "tempC": "19",
                    "tempF": "67",
                    "time": "1800",
                    "uvIndex": "0",
                    "visibility": "10",
                    "visibilityMiles": "6",
                    "weatherCode": "113",
                    "weatherDesc": [
                        {
                            "value": "Sunny"
                        }
                    ],
                    "weatherIconUrl": [
                        {
                            "value": ""
                        }
                    ],
                    "winddir16Point": "SSW",
                    "winddirDegree": "207",
                    "windspeedKmph": "11",
                    "windspeedMiles": "7"
                },
                {
                    "DewPointC": "3",
                    "DewPointF": "37",
                    "FeelsLikeC": "16",
                    "FeelsLikeF": "60",
                    "HeatIndexC": "16",
                    "HeatIndexF": "60",
                    "WindChillC": "16",
                    "WindChillF": "60",
                    "WindGustKmph": "11",
                    "WindGustMiles": "7",
                    "chanceoffog": "0",
                    "chanceoffrost": "0",
                    "chanceofhightemp": "0",
                    "chanceofovercast": "0",
                    "chanceofrain": "0",
                    "chanceofremdry": "80",
                    "chanceofsnow": "0",
                    "chanceofsunshine": "90",
                    "chanceofthunder": "0",
                    "chanceofwindy": "0",
                    "cloudcover": "13",
                    "diffRad": "15.2",
                    "humidity": "43",
                    "precipInches": "0.0",
                    "precipMM": "0.0",
                    "pressure": "1003",
                    "pressureInches": "30",
                    "shortRad": "42.1",
                    "tempC": "16",
                    "tempF": "60",
                    "time": "2100",
                    "uvIndex": "0",
                    "visibility": "10",
                    "visibilityMiles": "6",
                    "weatherCode": "113",
                    "weatherDesc": [
                        {
                            "value": "Clear "
                        }
                    ],
                    "weatherIconUrl": [
                        {
                            "value": ""
                        }
                    ],
                    "winddir16Point": "W",
                    "winddirDegree": "269",
                    "windspeedKmph": "5",
                    "windspeedMiles": "3"
                }
            ],
            "maxtempC": "23",
            "maxtempF": "73",
            "mintempC": "7",
            "mintempF": "45",
            "sunHour": "11.0",
            "totalSnow_cm": "0.0",
            "uvIndex": "1"
        }
    ]
}
